multiplexer/2 to 1 mux/mux2_1.v
module mux2_1(i0, i1, s, y);
    input wire i0, i1, s;
    output reg y;

    always @(i0 or i1 or s)
    begin
        if(s)
            y = i1;
        else
            y = i0;
    end    

endmodule

multiplexer/2 to 1 mux/mux2_1_testbench.v
//Testbench for 2 to 1 multiplexer
`include "mux2_1.v"

module testbench;
    wire y;
    reg i0, i1, s;
    mux2_1 name(.y(y), .i0(i0), .i1(i1), .s(s));

    initial 
    begin
        $dumpfile("mux2_1.vcd");
        $dumpvars(0, testbench);
        i0 = 1'b0;
        i1 = 1'b0;
        s = 1'b0;
        #100 $finish;    
    end
    
    always #40 i0 = ~i0;
    always #20 i1 = ~i1;
    always #10 s = ~s;
    always @(i0 or i1 or s)
    $monitor("At time = %t, Output = %d", $time, y);
endmodule

//iverilog -o mux2_1_testbench.vvp mux2_1_testbench.v
//vvp mux2_1_testbench.vvp

multiplexer/2 to 1 mux/mux2_1.vcd
$date
	Sun Nov 27 21:03:01 2022
$end
$version
	Icarus Verilog
$end
$timescale
	1s
$end
$scope module testbench $end
$var wire 1 ! y $end
$var reg 1 " i0 $end
$var reg 1 # i1 $end
$var reg 1 $ s $end
$scope module name $end
$var wire 1 " i0 $end
$var wire 1 # i1 $end
$var wire 1 $ s $end
$var reg 1 ! y $end
$upscope $end
$upscope $end
$enddefinitions $end
$comment Show the parameter values. $end
$dumpall
$end
#0
$dumpvars
0$
0#
0"
0!
$end
#10
1$
#20
0$
1#
#30
1!
1$
#40
0$
0#
1"
#50
0!
1$
#60
1!
0$
1#
#70
1$
#80
0!
0$
0#
0"
#90
1$
#100
0$
1#
