4-bit ALU/alu_4bit.v
// Verilog code for 4-bit ALU

module alu (input clk,
    input reset,
    input [3:0] a, 
    input [3:0] b, 
    input [1:0] sel,
    output [3:0] out,
    output overflow);

    reg [3:0] result;
    wire [4:0] temp;

    assign out = result;
    assign temp = {1'b0,a} + {1'b0,b};
    assign overflow = temp[4];

    always @(posedge clk)
        begin
            if (reset == 1'b0)
                case (sel)
                   2'b00: result <= a + b;
                   2'b01: result <= a - b;
                   2'b10: result <= a * b;
                   2'b11: result <= a / b;
                endcase 
            else
                result <= 4'b0000;
 
        end

endmodule

4-bit ALU/alu_4bit_testbench.v
// Testbench for 4-bit ALU

`include "alu_4bit.v"

module testbench;
    reg clk;
    reg reset;
    reg [3:0] a, b;
    reg [1:0] sel;
    wire [3:0] out;
    wire overflow;

    alu uut (clk, reset, a, b, sel, out, overflow);

    initial clk = 0;
    always #1 clk = ~clk;
      
    initial begin

        $dumpfile("alu_4bit.vcd");
        $dumpvars(0, testbench);

        reset = 1'b0;
        a = 4'b0000;
        b = 4'b0000;
        sel = 2'b00;

        #10;
        a = 4'b0001;
        b = 4'b0001;
        sel = 2'b00;

        #10;
        a = 4'b1111;
        b = 4'b1111;
        sel = 2'b00;

        #2;
        reset = 1'b1;

        #2;
        reset = 1'b0;
        a = 4'b0000;
        b = 4'b0000;
        sel = 2'b01;

        #10;
        a = 4'b0001;
        b = 4'b0001;
        sel = 2'b01;

        #10;
        a = 4'b0001;
        b = 4'b0011;
        sel = 2'b01;


        #10$finish;

    end

endmodule

//iverilog -o alu_4bit_testbench.vvp alu_4bit_testbench.v
//vvp alu_4bit_testbench.vvp

4-bit ALU/alu_4bit.vcd
$date
	Tue Mar 07 14:12:46 2023
$end
$version
	Icarus Verilog
$end
$timescale
	1s
$end
$scope module testbench $end
$var wire 1 ! overflow $end
$var wire 4 " out [3:0] $end
$var reg 4 # a [3:0] $end
$var reg 4 $ b [3:0] $end
$var reg 1 % clk $end
$var reg 1 & reset $end
$var reg 2 ' sel [1:0] $end
$scope module uut $end
$var wire 4 ( a [3:0] $end
$var wire 4 ) b [3:0] $end
$var wire 1 % clk $end
$var wire 4 * out [3:0] $end
$var wire 1 & reset $end
$var wire 2 + sel [1:0] $end
$var wire 5 , temp [4:0] $end
$var wire 1 ! overflow $end
$var reg 4 - result [3:0] $end
$upscope $end
$upscope $end
$enddefinitions $end
$comment Show the parameter values. $end
$dumpall
$end
#0
$dumpvars
bx -
b0 ,
b0 +
bx *
b0 )
b0 (
b0 '
0&
0%
b0 $
b0 #
bx "
0!
$end
#1
b0 "
b0 *
b0 -
1%
#2
0%
#3
1%
#4
0%
#5
1%
#6
0%
#7
1%
#8
0%
#9
1%
#10
0%
b1 $
b1 )
b10 ,
b1 #
b1 (
#11
b10 "
b10 *
b10 -
1%
#12
0%
#13
1%
#14
0%
#15
1%
#16
0%
#17
1%
#18
0%
#19
1%
#20
1!
0%
b1111 $
b1111 )
b11110 ,
b1111 #
b1111 (
#21
b1110 "
b1110 *
b1110 -
1%
#22
0%
1&
#23
b0 "
b0 *
b0 -
1%
#24
0!
0%
b1 '
b1 +
b0 $
b0 )
b0 ,
b0 #
b0 (
0&
#25
1%
#26
0%
#27
1%
#28
0%
#29
1%
#30
0%
#31
1%
#32
0%
#33
1%
#34
0%
b1 $
b1 )
b10 ,
b1 #
b1 (
#35
1%
#36
0%
#37
1%
#38
0%
#39
1%
#40
0%
#41
1%
#42
0%
#43
1%
#44
0%
b100 ,
b11 $
b11 )
#45
b1110 "
b1110 *
b1110 -
1%
