jk latch/jk_latch.v
module jk_latch(j, k, clk, reset, q);

    input j, k, clk, reset;
    output reg q;

    always @(posedge clk)
      if(reset == 1)
        q <= 0;
      else
        case ({j,k})
          2'b00: q <= q;
          2'b01: q <= 0;
          2'b10: q <= 1;
          2'b11: q <= ~q;
        endcase
endmodule

jk latch/jk_latch_testbench.v
//Testbench for JK latch
`include "jk_latch.v"

module testbench;
    reg j;
    reg k;
    reg clk;
    reg reset;

    initial clk = 0;
    always #5 clk = ~clk;

    jk_latch jk0 (.j(j), .k(k), .clk(clk), .reset(reset), .q(q));

    initial begin
        reset <= 1;
        #10 reset = 0;
    end

    initial 
    begin
        $dumpfile("jk_latch.vcd");
        $dumpvars(0, testbench);

        j <= 1;
        k <= 0;

        #20 j <= 0;
            k <= 0;
        #20 j <= 0;
            k <= 1;
        #20 j <= 1;
            k <= 1;

        #40 $finish;
    end
endmodule

//iverilog -o jk_latch_testbench jk_latch_testbench.v
//vvp jk_latch_testbench

jk latch/jk_latch.vcd
$date
	Tue Jan 24 23:09:23 2023
$end
$version
	Icarus Verilog
$end
$timescale
	1s
$end
$scope module testbench $end
$var wire 1 ! q $end
$var reg 1 " clk $end
$var reg 1 # j $end
$var reg 1 $ k $end
$var reg 1 % reset $end
$scope module jk0 $end
$var wire 1 " clk $end
$var wire 1 # j $end
$var wire 1 $ k $end
$var wire 1 % reset $end
$var reg 1 ! q $end
$upscope $end
$upscope $end
$enddefinitions $end
$comment Show the parameter values. $end
$dumpall
$end
#0
$dumpvars
1%
0$
1#
0"
x!
$end
#5
0!
1"
#10
0"
0%
#15
1!
1"
#20
0#
0"
#25
1"
#30
0"
#35
1"
#40
1$
0"
#45
0!
1"
#50
0"
#55
1"
#60
1#
0"
#65
1!
1"
#70
0"
#75
0!
1"
#80
0"
#85
1!
1"
#90
0"
#95
0!
1"
