full adder/full_adder.v
module full_adder(a, b, cin, sum, cout);
    input a, b, cin;
    output sum, cout;
    wire w, x, y;
    half_adder h1(w, x, a, b);
    half_adder h2(sum, y, w, cin);
    or(cout, x, y);
endmodule

module half_adder(S, C, A, B);
    input A, B;
    output S, C;
    xor(S, A, B);
    and(C, A, B);
endmodule

full adder/full_adder_testbench.v
//Test bench for halfadder
`include "full_adder.v"

module testbench;
    reg a, b, cin;
    wire sum, cout;
    
    full_adder add1(a, b, cin, sum, cout);
    
    initial 
    begin
      $dumpfile("full_adder.vcd");
      $dumpvars(0, testbench);
      a = 1'b0; b = 1'b0; cin = 1'b0; 
      #2;
      a = 1'b0; b = 1'b1; cin = 1'b0;
      #2;
      a = 1'b1; b = 1'b0; cin = 1'b0;
      #2;
      a = 1'b1; b = 1'b1; cin = 1'b0;
      #2;
      a = 1'b0; b = 1'b0; cin = 1'b1;
      #2;
      a = 1'b0; b = 1'b1; cin = 1'b1;
      #2;
      a = 1'b1; b = 1'b0; cin = 1'b1;
      #2;
      a = 1'b1; b = 1'b1; cin = 1'b1;
    end
endmodule

//iverilog -o full_adder_testbench.vvp full_adder_testbench.v
//vvp full_adder_testbench.vvp

full adder/full_adder.vcd
$date
	Sun Nov 20 18:54:59 2022
$end
$version
	Icarus Verilog
$end
$timescale
	1s
$end
$scope module testbench $end
$var wire 1 ! sum $end
$var wire 1 " cout $end
$var reg 1 # a $end
$var reg 1 $ b $end
$var reg 1 % cin $end
$scope module add1 $end
$var wire 1 # a $end
$var wire 1 $ b $end
$var wire 1 % cin $end
$var wire 1 " cout $end
$var wire 1 & y $end
$var wire 1 ' x $end
$var wire 1 ( w $end
$var wire 1 ! sum $end
$scope module h1 $end
$var wire 1 # A $end
$var wire 1 $ B $end
$var wire 1 ' C $end
$var wire 1 ( S $end
$upscope $end
$scope module h2 $end
$var wire 1 ( A $end
$var wire 1 % B $end
$var wire 1 & C $end
$var wire 1 ! S $end
$upscope $end
$upscope $end
$upscope $end
$enddefinitions $end
$comment Show the parameter values. $end
$dumpall
$end
#0
$dumpvars
0(
0'
0&
0%
0$
0#
0"
0!
$end
#2
1!
1(
1$
#4
0$
1#
#6
0!
1"
0(
1'
1$
#8
0"
1!
0'
1%
0$
0#
#10
1"
0!
1&
1(
1$
#12
0$
1#
#14
1!
0&
0(
1'
1$
