full subtractor/full_sub.v
module full_sub(a, b, diff, bin, bout);
    input a, b, bin;
    output diff, bout;
    wire w, x, y;
    half_sub h1(w, x, a, b);
    half_sub h2(diff, y, w, bin);
    or(bout, x, y);
endmodule


module half_sub(Diff, Borrow, A, B);
    input A, B;
    output Diff, Borrow;
    wire inverse_A;
    xor x1(Diff, A, B);
    not n1(inverse_A,A);
    and a1(Borrow, inverse_A, B);
endmodule

full subtractor/full_sub_testbench.v
//Test bench for full subtractor
`include "full_sub.v"

module testbench;
    reg a, b, bin;
    wire diff, bout;
    
    full_sub sub1(a, b, diff, bin, bout);
    
    initial 
    begin
      $dumpfile("full_sub.vcd");
      $dumpvars(0, testbench);
      a = 1'b0; b = 1'b0; bin = 1'b0; 
      #2;
      a = 1'b0; b = 1'b1; bin = 1'b0;
      #2;
      a = 1'b1; b = 1'b0; bin = 1'b0;
      #2;
      a = 1'b1; b = 1'b1; bin = 1'b0;
      #2;
      a = 1'b0; b = 1'b0; bin = 1'b1;
      #2;
      a = 1'b0; b = 1'b1; bin = 1'b1;
      #2;
      a = 1'b1; b = 1'b0; bin = 1'b1;
      #2;
      a = 1'b1; b = 1'b1; bin = 1'b1;
    end
endmodule

//iverilog -o full_sub_testbench.vvp full_sub_testbench.v
//vvp full_sub_testbench.vvp

full subtractor/full_sub.vcd
$date
	Mon Nov 21 00:11:00 2022
$end
$version
	Icarus Verilog
$end
$timescale
	1s
$end
$scope module testbench $end
$var wire 1 ! diff $end
$var wire 1 " bout $end
$var reg 1 # a $end
$var reg 1 $ b $end
$var reg 1 % bin $end
$scope module sub1 $end
$var wire 1 # a $end
$var wire 1 $ b $end
$var wire 1 % bin $end
$var wire 1 " bout $end
$var wire 1 & y $end
$var wire 1 ' x $end
$var wire 1 ( w $end
$var wire 1 ! diff $end
$scope module h1 $end
$var wire 1 # A $end
$var wire 1 $ B $end
$var wire 1 ' Borrow $end
$var wire 1 ( Diff $end
$var wire 1 ) inverse_A $end
$upscope $end
$scope module h2 $end
$var wire 1 ( A $end
$var wire 1 % B $end
$var wire 1 & Borrow $end
$var wire 1 ! Diff $end
$var wire 1 * inverse_A $end
$upscope $end
$upscope $end
$upscope $end
$enddefinitions $end
$comment Show the parameter values. $end
$dumpall
$end
#0
$dumpvars
1*
1)
0(
0'
0&
0%
0$
0#
0"
0!
$end
#2
1!
0*
1"
1(
1'
1$
#4
0"
0'
0)
0$
1#
#6
0!
1*
0(
1$
#8
1"
1!
1&
1)
1%
0$
0#
#10
0&
0!
0*
1(
1'
1$
#12
0"
0'
0)
0$
1#
#14
1"
1&
1!
1*
0(
1$
