sr latch/sr_latch.v
module sr_latch(r, s, clk, reset, q);

input r, s, clk, reset;
output reg q;

always @(posedge clk)
  if(reset == 1)
    q <= 0;
  else
    case ({s,r})
      2'b00: q <= q;
      2'b01: q <= 0;
      2'b10: q <= 1;
      2'b11: q <= 1'bZ;
    endcase
endmodule

sr latch/sr_latch_testbench.v
//Testbench for SR latch
`include "sr_latch.v"

module testbench;

    reg s;
    reg r;
    reg clk;
    reg reset;

    initial clk = 0;
    always #5 clk = ~clk;

    sr_latch sr0 (.s(s), .r(r), .clk(clk), .reset(reset), .q(q));
    
    initial begin
        reset <= 1;
        #10 reset = 0;
    end

    initial begin
        s <= 1;
        r <= 0;

        #20 s <= 0;
            r <= 0;
        #20 s <= 0;
            r <= 1;
        #20 s <= 1;
            r <= 1;
        $finish
    end

endmodule

sr latch/sr_latch.vcd
$date
	Tue Jan 24 23:05:11 2023
$end
$version
	Icarus Verilog
$end
$timescale
	1s
$end
$scope module testbench $end
$var wire 1 ! q $end
$var reg 1 " clk $end
$var reg 1 # r $end
$var reg 1 $ reset $end
$var reg 1 % s $end
$scope module sr0 $end
$var wire 1 " clk $end
$var wire 1 # r $end
$var wire 1 $ reset $end
$var wire 1 % s $end
$var reg 1 ! q $end
$upscope $end
$upscope $end
$enddefinitions $end
$comment Show the parameter values. $end
$dumpall
$end
#0
$dumpvars
1%
1$
0#
0"
x!
$end
#5
0!
1"
#10
0"
0$
#15
1!
1"
#20
0%
0"
#25
1"
#30
0"
#35
1"
#40
1#
0"
#45
0!
1"
#50
0"
#55
1"
#60
1%
0"
#65
z!
1"
